gitbugactions/__init__.py
gitbugactions/actions/__init__.py
gitbugactions/actions/action.py
gitbugactions/actions/actions.py
gitbugactions/actions/cpp/__init__.py
gitbugactions/actions/cpp/cmake_workflow.py
gitbugactions/actions/csharp/dotnet_workflow.py
gitbugactions/actions/csharp/helpers/__init__.py
gitbugactions/actions/csharp/helpers/dotnet_project_analyzer.py
gitbugactions/actions/go/__init__.py
gitbugactions/actions/go/go_workflow.py
gitbugactions/actions/java/__init__.py
gitbugactions/actions/java/gradle_workflow.py
gitbugactions/actions/java/maven_workflow.py
gitbugactions/actions/multi/__init__.py
gitbugactions/actions/multi/junitxmlparser.py
gitbugactions/actions/multi/testparser.py
gitbugactions/actions/multi/unknown_workflow.py
gitbugactions/actions/npm/__init__.py
gitbugactions/actions/npm/npm_jest_workflow.py
gitbugactions/actions/npm/npm_mocha_workflow.py
gitbugactions/actions/npm/npm_vitest_workflow.py
gitbugactions/actions/npm/npm_workflow.py
gitbugactions/actions/npm/npm_workflow_factory.py
gitbugactions/actions/python/__init__.py
gitbugactions/actions/python/pytest_workflow.py
gitbugactions/actions/python/unittest_workflow.py
gitbugactions/actions/rust/__init__.py
gitbugactions/actions/rust/cargo_workflow.py
gitbugactions/actions/templates/__init__.py
gitbugactions/actions/templates/languages/__init__.py
gitbugactions/actions/templates/languages/base.py
gitbugactions/actions/templates/languages/c/__init__.py
gitbugactions/actions/templates/languages/c/c.py
gitbugactions/actions/templates/languages/cmake/__init__.py
gitbugactions/actions/templates/languages/cmake/cmake.py
gitbugactions/actions/templates/languages/cmake/cmake.yml
gitbugactions/actions/templates/languages/cpp/__init__.py
gitbugactions/actions/templates/languages/cpp/cpp.py
gitbugactions/actions/templates/languages/csharp/__init__.py
gitbugactions/actions/templates/languages/csharp/csharp.py
gitbugactions/actions/templates/template_workflows.py
gitbugactions/actions/workflow.py
gitbugactions-4.4.5.dist-info/LICENSE
gitbugactions-4.4.5.dist-info/METADATA
gitbugactions-4.4.5.dist-info/WHEEL
gitbugactions-4.4.5.dist-info/RECORD
