Metadata-Version: 2.3
Name: gitbugactions
Version: 4.4.5
Summary: A tool that builds executable code datasets with GitHub Actions.
License: MIT
Author: Nuno Saavedra
Author-email: nuno.saavedra@tecnico.ulisboa.pt
Requires-Python: >=3.12,<4.0
Classifier: License :: OSI Approved :: MIT License
Classifier: Programming Language :: Python :: 3
Classifier: Programming Language :: Python :: 3.12
Classifier: Programming Language :: Python :: 3.13
Requires-Dist: PyGithub (==2.6.1)
Requires-Dist: PyYAML (==6.0.2)
Requires-Dist: attrs (>=25.0.0,<26.0.0)
Requires-Dist: docker (==7.1.0)
Requires-Dist: fire (==0.7.0)
Requires-Dist: jsonschema (>=4.23.0,<5.0.0)
Requires-Dist: junitparser (==3.2.0)
Requires-Dist: nltk (==3.9.1)
Requires-Dist: numpy (==2.2.5)
Requires-Dist: pandas (==2.2.3)
Requires-Dist: pygit2 (==1.18.0)
Requires-Dist: pytest-ordering (>=0.6,<0.7)
Requires-Dist: referencing (>=0.36.0,<0.37.0)
Requires-Dist: schedule (>=1.2.2,<2.0.0)
Requires-Dist: tqdm (==4.67.1)
Requires-Dist: unidiff (==0.7.5)
Requires-Dist: urllib3 (==2.4.0)
